sportradar_api/__init__.py
sportradar_api/main.py
sportradar_api/soccer_extended/__init__.py
sportradar_api/soccer_extended/soccer_extended.py
sportradar_api/soccer_extended/soccer_extended_pandas.py
sportradar_api/utils/__init__.py
sportradar_api/utils/utils.py
sportradar_api-0.2.8.dist-info/METADATA
sportradar_api-0.2.8.dist-info/WHEEL
sportradar_api-0.2.8.dist-info/LICENSE
sportradar_api-0.2.8.dist-info/RECORD
