Metadata-Version: 2.1
Name: sportradar-api
Version: 0.2.8
Summary: Lightweight wrapper for Sportradar API
Home-page: https://felipeall.github.io/sportradar-api
License: MIT
Author: Felipe Allegretti
Author-email: felipe@allegretti.me
Requires-Python: >=3.9,<4.0
Classifier: License :: OSI Approved :: MIT License
Classifier: Operating System :: OS Independent
Classifier: Programming Language :: Python
Classifier: Programming Language :: Python :: 3
Classifier: Programming Language :: Python :: 3.9
Classifier: Programming Language :: Python :: 3.10
Classifier: Programming Language :: Python :: 3.11
Classifier: Programming Language :: Python :: 3
Classifier: Topic :: Software Development :: Libraries
Requires-Dist: flatten-json (==0.1.13)
Requires-Dist: pandas (==1.5.3)
Requires-Dist: requests (==2.31.0)
Requires-Dist: urllib3 (==1.26.16)
Project-URL: Repository, https://github.com/felipeall/sportradar-api
